filio/__init__.py
filio/__main__.py
filio/utils.py
Filio-1.0.0.dist-info/LICENSE
Filio-1.0.0.dist-info/METADATA
Filio-1.0.0.dist-info/WHEEL
Filio-1.0.0.dist-info/entry_points.txt
Filio-1.0.0.dist-info/top_level.txt
Filio-1.0.0.dist-info/RECORD
