Metadata-Version: 2.1
Name: Filio
Version: 1.0.0
Summary: a cli python tool which checks for empty & broken files
Home-page: https://github.com/nerdloco/filio
Author: nerdloco
Author-email: gibsonruitiari@gmail.com
License: MIT
Platform: UNKNOWN
Classifier: License :: OSI Approved :: MIT License
Classifier: Programming Language :: Python :: 3
Requires-Dist: click
Requires-Dist: asyncio
